skexplain/__init__.py
skexplain/common/__init__.py
skexplain/common/attributes.py
skexplain/common/contrib_utils.py
skexplain/common/dataset.py
skexplain/common/importance_utils.py
skexplain/common/io.py
skexplain/common/metrics.py
skexplain/common/models.py
skexplain/common/multiprocessing_utils.py
skexplain/common/utils.py
skexplain/common/data/road_surface_data.csv
skexplain/common/models/GradientBoostingClassifier.pkl
skexplain/common/models/LogisticRegression.pkl
skexplain/common/models/RandomForestClassifier.pkl
skexplain/main/__init__.py
skexplain/main/explain_toolkit.py
skexplain/main/global_explainer.py
skexplain/main/lime_fast.py
skexplain/main/local_explainer.py
skexplain/main/tree_interpreter.py
skexplain/main/PermutationImportance/__init__.py
skexplain/main/PermutationImportance/abstract_runner.py
skexplain/main/PermutationImportance/data_verification.py
skexplain/main/PermutationImportance/error_handling.py
skexplain/main/PermutationImportance/metrics.py
skexplain/main/PermutationImportance/multiprocessing_utils.py
skexplain/main/PermutationImportance/permutation_importance.py
skexplain/main/PermutationImportance/result.py
skexplain/main/PermutationImportance/scoring_strategies.py
skexplain/main/PermutationImportance/selection_strategies.py
skexplain/main/PermutationImportance/sequential_selection.py
skexplain/main/PermutationImportance/sklearn_api.py
skexplain/main/PermutationImportance/utils.py
skexplain/plot/__init__.py
skexplain/plot/_beeswarm.py
skexplain/plot/_box_and_whisker.py
skexplain/plot/_kde_2d.py
skexplain/plot/base_plotting.py
skexplain/plot/dependence.py
skexplain/plot/plot_2D.py
skexplain/plot/plot_feature_contributions.py
skexplain/plot/plot_interpret_curves.py
skexplain/plot/plot_permutation_importance.py
skexplain/plot/plot_sobol.py
scikit_explain-0.1.4.dist-info/LICENSE
scikit_explain-0.1.4.dist-info/METADATA
scikit_explain-0.1.4.dist-info/WHEEL
scikit_explain-0.1.4.dist-info/top_level.txt
scikit_explain-0.1.4.dist-info/RECORD
