Metadata-Version: 2.1
Name: scikit-explain
Version: 0.1.4
Summary: A user-friendly python package for computing and plotting machine learning explainability output.
Home-page: https://github.com/monte-flora/scikit-explain/
Author: Montgomery Flora
Author-email: monte.flora@noaa.gov
License: MIT
Platform: UNKNOWN
Classifier: License :: OSI Approved :: MIT License
Classifier: Programming Language :: Python :: 3
Classifier: Programming Language :: Python :: 3.8
Requires-Python: >=3.8.0
License-File: LICENSE
Requires-Dist: numpy
Requires-Dist: pandas
Requires-Dist: scikit-learn (>=1.0.0)
Requires-Dist: matplotlib
Requires-Dist: shap (>=0.30.0)
Requires-Dist: xarray (>=0.16.0)
Requires-Dist: tqdm
Requires-Dist: ipywidgets
Requires-Dist: statsmodels
Requires-Dist: seaborn (>=0.11.0)
Provides-Extra: interactive
Requires-Dist: jupyter ; extra == 'interactive'
